[
    {
        "id": 17928554191447906,
        "created_at": 1605671034,
        "text": "\ud83e\udd2e\ud83e\udd2e\ud83e\udd2e\ud83e\udd2e\ud83e\udd2e",
        "owner": {
            "id": "1181313986",
            "is_verified": false,
            "profile_pic_url": "https://instagram.faqp1-1.fna.fbcdn.net/v/t51.2885-19/s150x150/122728830_2881481285288751_5918158486797182894_n.jpg?_nc_ht=instagram.faqp1-1.fna.fbcdn.net&_nc_ohc=TXpoVsRONWkAX-xcLaA&_nc_tp=25&oh=a7d0352d485c5ecae93d8e32807e7955&oe=5FDD4D99",
            "username": "just_pabla"
        },
        "likes_count": 1,
        "answers": []
    },
    {
        "id": 17893186579697104,
        "created_at": 1605663240,
        "text": "@felipeharboe #niperdonniolvido \ud83e\udd22\ud83d\udc4e",
        "owner": {
            "id": "3143015647",
            "is_verified": false,
            "profile_pic_url": "https://instagram.faqp1-1.fna.fbcdn.net/v/t51.2885-19/s150x150/115796053_422312595393636_6593791026486589994_n.jpg?_nc_ht=instagram.faqp1-1.fna.fbcdn.net&_nc_ohc=EORssRtraTEAX9DTt0b&_nc_tp=25&oh=1ca5e9be61119935152a2e0120b6041b&oe=5FDE30E6",
            "username": "spizarrov"
        },
        "likes_count": 3,
        "answers": []
    },
    {
        "id": 17875823884954706,
        "created_at": 1605652849,
        "text": "@felipeharboe \ud83e\udd2e\ud83e\udd2e\ud83e\udd2e\ud83e\udd2e\ud83e\udd2e\ud83e\udd2e\ud83e\udd21\ud83e\udd21",
        "owner": {
            "id": "8602778235",
            "is_verified": false,
            "profile_pic_url": "https://instagram.faqp1-1.fna.fbcdn.net/v/t51.2885-19/s150x150/118825546_174250230881818_8076782140493577799_n.jpg?_nc_ht=instagram.faqp1-1.fna.fbcdn.net&_nc_ohc=7uspKSluRecAX83V816&_nc_tp=25&oh=5ddb5e411f5f47bcb4253373e513622a&oe=5FDFDFFE",
            "username": "exc0mulg4d0_hid4lg0"
        },
        "likes_count": 3,
        "answers": []
    },
    {
        "id": 17888695534783379,
        "created_at": 1605649174,
        "text": "Este saco de weas.......es un Payaso habla de principios y valores y quiere vender al pa\u00eds con el tpp11 un VENDIDO como su gobierno (NUEVA PORQUERIA)y toda su cag\u00e1 de partido...PPD....que se vaya ....AHORA",
        "owner": {
            "id": "32108085022",
            "is_verified": false,
            "profile_pic_url": "https://instagram.faqp1-1.fna.fbcdn.net/v/t51.2885-19/s150x150/91107674_863618980772712_7622096937713401856_n.jpg?_nc_ht=instagram.faqp1-1.fna.fbcdn.net&_nc_ohc=6UMyqzsVE4kAX8NEel1&_nc_tp=25&oh=8188a9467398c92de8b1560aab5da070&oe=5FDF209D",
            "username": "reca1980"
        },
        "likes_count": 2,
        "answers": []
    }
]